byuimage.py
byuimage-0.4.1.dist-info/METADATA
byuimage-0.4.1.dist-info/WHEEL
byuimage-0.4.1.dist-info/licenses/LICENSE
byuimage-0.4.1.dist-info/RECORD
