Metadata-Version: 2.4
Name: byuimage
Version: 0.4.1
Summary: Simple Image processing library, used for teaching people how to program
License: MIT
License-File: LICENSE
Author: Daniel Zappala
Author-email: daniel.zappala@gmail.com
Requires-Python: >=3.10,<4.0
Classifier: License :: OSI Approved :: MIT License
Classifier: Programming Language :: Python :: 3
Classifier: Programming Language :: Python :: 3.10
Classifier: Programming Language :: Python :: 3.11
Classifier: Programming Language :: Python :: 3.12
Classifier: Programming Language :: Python :: 3.13
Classifier: Programming Language :: Python :: 3.14
Requires-Dist: pillow (>=11.0.0,<12.0.0)
